pyscript_dot_com/__init__.py
pyscript_dot_com/auth.py
pyscript_dot_com/cli.py
pyscript_dot_com/config.py
pyscript_dot_com/renderers.py
pyscript_dot_com/service.py
pyscript_dot_com/utils.py
pyscript_dot_com/plugins/__init__.py
pyscript_dot_com/plugins/config.py
pyscript_dot_com/plugins/copy.py
pyscript_dot_com/plugins/delete.py
pyscript_dot_com/plugins/download.py
pyscript_dot_com/plugins/info.py
pyscript_dot_com/plugins/list.py
pyscript_dot_com/plugins/login.py
pyscript_dot_com/plugins/logout.py
pyscript_dot_com/plugins/ping.py
pyscript_dot_com/plugins/setup.py
pyscript_dot_com/plugins/upload.py
pyscript_dot_com/plugins/version.py
pyscript_dot_com/plugins/view.py
pyscript_dot_com_cli-0.1.0.dist-info/LICENSE
pyscript_dot_com_cli-0.1.0.dist-info/METADATA
pyscript_dot_com_cli-0.1.0.dist-info/WHEEL
pyscript_dot_com_cli-0.1.0.dist-info/entry_points.txt
pyscript_dot_com_cli-0.1.0.dist-info/top_level.txt
pyscript_dot_com_cli-0.1.0.dist-info/RECORD
