Metadata-Version: 2.1
Name: pyscript-dot-com-cli
Version: 0.1.0
Summary: Command Line Interface for PyScript.com
Home-page: https://pyscript.com
Author: Fabio Pliger, Nicholas Tollervey, Fabio Rosado, Madhur Tandon
Author-email: fpliger@anaconda.com, ntollervey@anaconda.com, frosado@anaconda.com, mtandon@anaconda.com
License: Apache-2.0
Project-URL: Documentation, https://docs.pyscript.net
Project-URL: Examples, https://pyscript.com/@examples
Project-URL: Homepage, https://pyscript.com
Project-URL: Repository, https://github.com/anaconda/pyscript-dot-com-issues
Keywords: pyscript,cli,pyscript.com,pyscript-cli,pyscript-dot-com
Classifier: Development Status :: 4 - Beta
Classifier: Environment :: Console
Classifier: Intended Audience :: Developers
Classifier: License :: OSI Approved :: Apache Software License
Classifier: Programming Language :: Python :: 3
Classifier: Programming Language :: Python :: 3.9
Classifier: Programming Language :: Python :: 3.10
Classifier: Topic :: Software Development :: Code Generators
Classifier: Topic :: Software Development :: Libraries :: Python Modules
Classifier: Topic :: Software Development :: Pre-processors
Requires-Python: >=3.9
License-File: LICENSE
Requires-Dist: pyscript-cli ==0.3.4
Requires-Dist: pydantic ==1.10.14
Requires-Dist: requests ==2.31.0
Requires-Dist: keyring ==24.3.1
Requires-Dist: cryptography ==42.0.5
Requires-Dist: cffi ==1.16.0
Requires-Dist: python-dotenv ==1.0.1
Requires-Dist: pyjwt ==2.8.0
Requires-Dist: rich ==13.4.1
Requires-Dist: typer ==0.9.0
Requires-Dist: argon2-cffi ==23.1.0 ; platform_system == "Linux"
Requires-Dist: pycryptodome ==3.20.0 ; platform_system == "Linux"
Requires-Dist: keyrings.cryptfile ==1.3.9 ; platform_system == "Linux"
Requires-Dist: SecretStorage >=3.3.3 ; platform_system == "Linux"
Provides-Extra: tests
Requires-Dist: pytest ==7.4.4 ; extra == 'tests'
Requires-Dist: pytest-recording ==0.13.1 ; extra == 'tests'
Requires-Dist: vcrpy ==6.0.1 ; extra == 'tests'
